{
    "id": "intro-to-facilitation",
    "title": "ศิลปะการอำนวยความสะดวก (Facilitation Skills) สำหรับผู้นำยุคใหม่",
    "category": "Leadership",
    "thumbnail": "https://images.unsplash.com/photo-1517048676732-d676936d9b2c?auto=format&fit=crop&q=80",
    "author": "ครูเด่น มาสเตอร์ฟา",
    "date": "22 มกราคม 2569",
    "createdAt": "2026-01-22T00:00:00Z",
    "readTime": "10 Min Read",
    "description": "เจาะลึกบทบาทผู้นำในฐานะ Facilitator เพื่อสร้างการมีส่วนร่วมและผลลัพธ์ที่ยั่งยืน",
    "tags": [
        "Leadership",
        "Facilitation",
        "Teamwork"
    ],
    "sections": [
        {
            "type": "heading",
            "content": "ทำไมผู้นำยุคใหม่ต้องมีทักษะ Facilitation?"
        },
        {
            "type": "text",
            "content": "ในโลกที่ซับซ้อนและเปลี่ยนแปลงรวดเร็ว การสั่งการจากบนลงล่าง (Top-down) อาจไม่เพียงพออีกต่อไป ผู้นำต้องเปลี่ยนบทบาทจาก 'ผู้สั่ง' เป็น 'ผู้อำนวยความสะดวก' เพื่อดึงศักยภาพที่แท้จริงของทีมงานออกมา"
        },
        {
            "type": "quote",
            "content": "ผู้นำที่ดีไม่ใช่ผู้ที่มีคำตอบให้ทุกคนเสมอ แต่คือผู้ที่รู้วิธีการพาให้ทุกคนไปพบคำตอบด้วยตนเอง",
            "author": "ครูเด่น มาสเตอร์ฟา"
        },
        {
            "type": "subheading",
            "content": "ความแตกต่างระหว่าง Leader และ Facilitator"
        },
        {
            "type": "list",
            "items": [
                "<strong>Leader:</strong> เน้นผลลัพธ์และการตัดสินใจ",
                "<strong>Facilitator:</strong> เน้นกระบวนการและการมีส่วนร่วม",
                "<strong>Modern Leader:</strong> ใช้ทั้งสองบทบาทควบคู่กันตามสถานการณ์"
            ]
        },
        {
            "type": "box",
            "variant": "info",
            "title": "💡 Tip: 3 หัวใจของ Facilitation",
            "items": [
                "Neutrality: ความเป็นกลาง ไม่ด่วนตัดสิน",
                "Active Listening: การฟังเชิงรุก",
                "Powerful Questioning: การตั้งคำถามที่ทรงพลัง"
            ]
        }
    ]
}